{
  "October" :
  [
    {
      "title": "Hero Hacks",
      "url": "https://organize.mlh.io/participants/events/4618-herohacks",
      "startDate": "October 2",
      "endDate": "October 4",
      "year": "2020",
      "city": "Remote",
      "host": "Major League Hacking",
      "length": "48",
      "size": "unknown",
      "travel": "no",
      "prize": "yes",
      "highSchoolers": "unknown",
      "cost": "free",
      "facebookURL": "https://www.facebook.com/MajorLeagueHacking",
      "twitterURL": "https://twitter.com/mlhacks",
      "notes": ""
    },
    {
      "title": "Miami Hacks",
      "url": "https://miamihacks.com/",
      "startDate": "October 2",
      "endDate": "October 4",
      "year": "2020",
      "city": "Remote",
      "host": "Florida International University",
      "length": "48",
      "size": "unknown",
      "travel": "no",
      "prize": "yes",
      "highSchoolers": "no",
      "cost": "free",
      "facebookURL": "https://www.facebook.com/acmfiu/",
      "twitterURL": "https://www.twitter.com/acmfiu",
      "notes": ""
    },
    {
      "title": "VandyHacks",
      "url": "https://vandyhacks.org/",
      "startDate": "October 2",
      "endDate": "October 4",
      "year": "2020",
      "city": "Remote",
      "host": "Vanderbilt University",
      "length": "36",
      "size": "unknown",
      "travel": "no",
      "prize": "yes",
      "highSchoolers": "unknown",
      "cost": "free",
      "facebookURL": "https://www.facebook.com/vandyhacks",
      "twitterURL": "https://www.twitter.com/vandyhacks",
      "notes": ""
    }
  ]
}